medialog.magneticpopup-1.1.1-py3.8-nspkg.pth
medialog/.DS_Store
medialog/magneticpopup/__init__.py
medialog/magneticpopup/adapters.py
medialog/magneticpopup/configure.zcml
medialog/magneticpopup/interfaces.py
medialog/magneticpopup/setuphandlers.py
medialog/magneticpopup/testing.py
medialog/magneticpopup/browser/__init__.py
medialog/magneticpopup/browser/configure.zcml
medialog/magneticpopup/browser/overrides/.gitkeep
medialog/magneticpopup/browser/static/.gitkeep
medialog/magneticpopup/browser/static/jquery.magnific-popup-min.js
medialog/magneticpopup/browser/static/jquery.magnific-popup.js
medialog/magneticpopup/browser/static/magnetic-popup.css
medialog/magneticpopup/browser/static/magnetic-popup.js
medialog/magneticpopup/locales/medialog.magneticpopup.pot
medialog/magneticpopup/locales/update.sh
medialog/magneticpopup/profiles/default/browserlayer.xml
medialog/magneticpopup/profiles/default/metadata.xml
medialog/magneticpopup/profiles/default/registry.xml
medialog/magneticpopup/profiles/uninstall/browserlayer.xml
medialog/magneticpopup/profiles/uninstall/registry.xml
medialog/magneticpopup/tests/__init__.py
medialog/magneticpopup/tests/test_robot.py
medialog/magneticpopup/tests/test_setup.py
medialog/magneticpopup/tests/robot/test_example.robot
medialog.magneticpopup-1.1.1.dist-info/METADATA
medialog.magneticpopup-1.1.1.dist-info/WHEEL
medialog.magneticpopup-1.1.1.dist-info/entry_points.txt
medialog.magneticpopup-1.1.1.dist-info/namespace_packages.txt
medialog.magneticpopup-1.1.1.dist-info/top_level.txt
medialog.magneticpopup-1.1.1.dist-info/RECORD
